MANIFEST.in
README.md
setup.cfg
setup.py
max_training_framework/__init__.py
max_training_framework/wml_setup.py
max_training_framework/wml_train.py
max_training_framework.egg-info/PKG-INFO
max_training_framework.egg-info/SOURCES.txt
max_training_framework.egg-info/dependency_links.txt
max_training_framework.egg-info/requires.txt
max_training_framework.egg-info/top_level.txt
max_training_framework.egg-info/zip-safe
max_training_framework/setup/__init__.py
max_training_framework/setup/config.json
max_training_framework/setup/instance_handling.py
max_training_framework/setup/service_handling.py
max_training_framework/setup/setup_functions.py
max_training_framework/setup/token_generate.py
max_training_framework/setup/yaml_handling.py
max_training_framework/utils/__init__.py
max_training_framework/utils/config.py
max_training_framework/utils/cos.py
max_training_framework/utils/debug.py
max_training_framework/utils/os_util.py
max_training_framework/utils/wml.py