Metadata-Version: 2.1
Name: max-training-framework
Version: 0.1.1
Summary: Training framework for the Model Asset Exchange
Home-page: https://github.com/IBM/Max-Training-Framework
Author: CODAIT
Author-email: ptitzler@us.ibm.com
License: Apache-2.0
Keywords: deep learning
Platform: UNKNOWN
Classifier: Development Status :: 5 - Production/Stable
Classifier: License :: OSI Approved :: Apache Software License
Classifier: Programming Language :: Python :: 3.6
Classifier: Programming Language :: Python :: 3.7
